groklog/__init__.py
groklog/args.py
groklog/filter_manager/__init__.py
groklog/filter_manager/exceptions.py
groklog/filter_manager/filter_manager.py
groklog/process_node/__init__.py
groklog/process_node/base.py
groklog/process_node/generic_process.py
groklog/process_node/shell_process.py
groklog/ui/filter_viewer.py
groklog/ui/scenes/__init__.py
groklog/ui/scenes/app.py
groklog/ui/scenes/base_app.py
groklog/ui/scenes/filter_creator.py
groklog/ui/scenes/scene_names.py
groklog/ui/streaming_text_box.py
groklog/ui/terminal.py
groklog/ui/theming.py
groklog/version.py
groklog-0.3.0.dist-info/entry_points.txt
groklog-0.3.0.dist-info/LICENSE
groklog-0.3.0.dist-info/WHEEL
groklog-0.3.0.dist-info/METADATA
groklog-0.3.0.dist-info/RECORD
