Metadata-Version: 2.1
Name: groklog
Version: 0.3.0
Summary: A tool for filtering logs quickly and easily
License: MIT
Author: Alex Thiel
Author-email: apocthiel@gmail.com
Requires-Python: >=3.8,<4.0
Classifier: License :: OSI Approved :: MIT License
Classifier: Programming Language :: Python :: 3
Classifier: Programming Language :: Python :: 3.8
Classifier: Programming Language :: Python :: 3.9
Requires-Dist: appdirs (>=1.4.4,<2.0.0)
Requires-Dist: asciimatics (>=1.13.0,<2.0.0)
Requires-Dist: pre-commit (>=2.13.0,<3.0.0)
Requires-Dist: pubsus (>=0.1.1,<0.2.0)
